{"sentiment": [{"line_number": 0, "original_text": "not only is it crucial for organisations to be held accountable for their exposure, but people should be given the information they\n", "sentiment": {"sentiment": "neutral", "confidence": 0.716634213924408}}, {"line_number": 1, "original_text": "require to make informed decisions on how their interaction with companies could impact our global environment\n", "sentiment": {"sentiment": "neutral", "confidence": 0.9752217531204224}}, {"line_number": 2, "original_text": "\n", "sentiment": {"sentiment": "neutral", "confidence": 0.9320765733718872}}, {"line_number": 3, "original_text": "\n", "sentiment": {"sentiment": "neutral", "confidence": 0.9320765733718872}}, {"line_number": 4, "original_text": "\n", "sentiment": {"sentiment": "neutral", "confidence": 0.9320765733718872}}, {"line_number": 5, "original_text": "\n", "sentiment": {"sentiment": "neutral", "confidence": 0.9320765733718872}}, {"line_number": 6, "original_text": " \n", "sentiment": {"sentiment": "neutral", "confidence": 0.9320765733718872}}], "key_phrases": [{"Score": 0.9999998807907247, "Text": "it"}, {"Score": 0.9999996423722521, "Text": "organisations"}, {"Score": 1.0, "Text": "their exposure"}, {"Score": 1.0, "Text": "people"}, {"Score": 1.0, "Text": "the information"}, {"Score": 1.0, "Text": "they"}, {"Score": 0.999999344349467, "Text": "informed decisions"}, {"Score": 0.9999986886999537, "Text": "their interaction"}, {"Score": 1.0, "Text": "companies"}], "topics": [{"topic": "009", "confidence": "1.0"}]}