{"sentiment": [{"line_number": 0, "original_text": "This has to happen now. Good to see a government willing to do something. Let's have the hard conversations now, then move on to\n", "sentiment": {"sentiment": "positive", "confidence": 0.5051504969596863}}, {"line_number": 1, "original_text": "a brighter, cleaner, smarter future for all. PS consider the TOP policy on housing and wealth taxation. it's the only way to free up\n", "sentiment": {"sentiment": "mixed", "confidence": 0.8418945074081421}}, {"line_number": 2, "original_text": "\n", "sentiment": {"sentiment": "neutral", "confidence": 0.9320765733718872}}, {"line_number": 3, "original_text": "people's finances from their homes, stop people being so scared of climate change destroying their equity, and will mean we have\n", "sentiment": {"sentiment": "mixed", "confidence": 0.7426666021347046}}, {"line_number": 4, "original_text": "more money to invest in new tech.\n", "sentiment": {"sentiment": "negative", "confidence": 0.577781617641449}}], "key_phrases": [{"Score": 0.9999881984200047, "Text": "This"}, {"Score": 0.999999642372309, "Text": "a government"}, {"Score": 0.9999997615814777, "Text": "something"}, {"Score": 0.9999475506632682, "Text": "'s"}, {"Score": 0.9999956687640322, "Text": "the hard conversations"}, {"Score": 0.9187228863865147, "Text": "a brighter, cleaner, smarter future"}, {"Score": 0.9828115350117975, "Text": "all"}, {"Score": 0.9999969005680498, "Text": "PS"}, {"Score": 0.9999999205271529, "Text": "the TOP policy"}, {"Score": 0.9998272364078676, "Text": "housing and wealth taxation"}, {"Score": 0.9999998807907247, "Text": "it"}, {"Score": 0.9999978939769494, "Text": "the only way"}, {"Score": 0.9999988079084972, "Text": "people"}, {"Score": 0.9999999403953606, "Text": "'s finances"}, {"Score": 0.9999997019768632, "Text": "their homes"}, {"Score": 0.9999920130413283, "Text": "people"}, {"Score": 0.9999734769077085, "Text": "climate change"}, {"Score": 1.0, "Text": "their equity"}, {"Score": 0.9999998807907247, "Text": "we"}, {"Score": 0.9999997615814777, "Text": "more money"}, {"Score": 0.9999988079088666, "Text": "new tech"}], "topics": [{"topic": "000", "confidence": "1.0"}]}