{"sentiment": [{"line_number": 0, "original_text": "I am relieved we have had a change of government and this proposal is in front of us. Thank you.\n", "sentiment": {"sentiment": "positive", "confidence": 0.742167592048645}}], "key_phrases": [{"Score": 1.0, "Text": "I"}, {"Score": 1.0, "Text": "we"}, {"Score": 1.0, "Text": "a change"}, {"Score": 1.0, "Text": "government"}, {"Score": 1.0, "Text": "this proposal"}, {"Score": 1.0, "Text": "front"}, {"Score": 1.0, "Text": "us"}, {"Score": 1.0, "Text": "you"}], "topics": [{"topic": "008", "confidence": "1.0"}]}