{"sentiment": [{"line_number": 0, "original_text": "While the 2050 date and the idea of staged five year emission budgets might convey a calm, considered process we need to keep in\n", "sentiment": {"sentiment": "neutral", "confidence": 0.899330735206604}}, {"line_number": 1, "original_text": "mind that right now in almost any given week in New Zealand we have housing, infrastructure and agricultural output being destroyed\n", "sentiment": {"sentiment": "negative", "confidence": 0.7218747735023499}}, {"line_number": 2, "original_text": "\n", "sentiment": {"sentiment": "neutral", "confidence": 0.9320765733718872}}, {"line_number": 3, "original_text": "by weather related cold, drought, flooding and wind with invasive species being enabled and diseases spreading. What we might plan\n", "sentiment": {"sentiment": "neutral", "confidence": 0.7116213440895081}}, {"line_number": 4, "original_text": "at our pace within our considerations of GDP and 'political reality' actually has no relation to the speed at which the climate is\n", "sentiment": {"sentiment": "neutral", "confidence": 0.660783052444458}}, {"line_number": 5, "original_text": "changing and the impacts are appearing. To do anything less than put into legislation the most ambitious emissions reductions we\n", "sentiment": {"sentiment": "neutral", "confidence": 0.767929196357727}}, {"line_number": 6, "original_text": "\n", "sentiment": {"sentiment": "neutral", "confidence": 0.9320765733718872}}, {"line_number": 7, "original_text": "can is to lose any chance of getting ahead of the pace of the changes we've already started. We throw not only caution to the wind,\n", "sentiment": {"sentiment": "negative", "confidence": 0.4893963038921356}}, {"line_number": 8, "original_text": "but the basis of our civilisation.\n", "sentiment": {"sentiment": "neutral", "confidence": 0.9878387451171875}}], "key_phrases": [{"Score": 0.9999959469043062, "Text": "the 2050 date"}, {"Score": 0.999999463558483, "Text": "the idea"}, {"Score": 0.9991773989329732, "Text": "five year emission budgets"}, {"Score": 0.996845848164678, "Text": "a calm"}, {"Score": 0.8213659574492851, "Text": "process"}, {"Score": 0.9969000651495549, "Text": "we"}, {"Score": 0.9999977350285647, "Text": "mind"}, {"Score": 0.9809100966805225, "Text": "almost any given week"}, {"Score": 0.9999999403953606, "Text": "New Zealand"}, {"Score": 0.9994301469118486, "Text": "we"}, {"Score": 0.9999252613624905, "Text": "housing"}, {"Score": 0.8190840179560999, "Text": "infrastructure"}, {"Score": 0.7659108200574853, "Text": "agricultural output"}, {"Score": 0.9917153789605615, "Text": "weather"}, {"Score": 0.9213456388762727, "Text": "cold, drought, flooding and wind"}, {"Score": 0.9999947548279805, "Text": "invasive species"}, {"Score": 0.9971038775810548, "Text": "diseases"}, {"Score": 0.999940398906774, "Text": "What"}, {"Score": 0.9999803308534772, "Text": "we"}, {"Score": 0.9999986886998684, "Text": "our pace"}, {"Score": 0.9999997019769058, "Text": "our considerations"}, {"Score": 0.9999594704850789, "Text": "GDP"}, {"Score": 0.9918243041806618, "Text": "political reality"}, {"Score": 0.9999986886996979, "Text": "no relation"}, {"Score": 0.9999984502818577, "Text": "the speed"}, {"Score": 0.9999998807907247, "Text": "which"}, {"Score": 0.9999171598291543, "Text": "the climate"}, {"Score": 0.9999992847448027, "Text": "the impacts"}, {"Score": 0.9997947637384105, "Text": "anything"}, {"Score": 0.9999933243243502, "Text": "legislation"}, {"Score": 0.999952081650176, "Text": "the most ambitious emissions"}, {"Score": 0.9999974966112362, "Text": "we"}, {"Score": 1.0, "Text": "any chance"}, {"Score": 0.9999998807907247, "Text": "the pace"}, {"Score": 0.9999996423722841, "Text": "the changes"}, {"Score": 0.9999996423722521, "Text": "we"}, {"Score": 0.9999996423722521, "Text": "We"}, {"Score": 0.939689164751091, "Text": "caution"}, {"Score": 0.999998807908554, "Text": "the wind"}, {"Score": 0.9999997615815062, "Text": "the basis"}, {"Score": 0.999951841814473, "Text": "our civilisation"}], "topics": [{"topic": "000", "confidence": "1.0"}]}