{"sentiment": [{"line_number": 0, "original_text": "The Bill's title should be changed to read: The Xero Emissions Bill because it must apply to all greenhouse gases not just carbon.\n", "sentiment": {"sentiment": "neutral", "confidence": 0.9493027925491333}}, {"line_number": 1, "original_text": "\n", "sentiment": {"sentiment": "neutral", "confidence": 0.9320765733718872}}, {"line_number": 2, "original_text": "The utmost urgency must be applied to setting up the Climate Change Commission. The changes set in motion by decades of global\n", "sentiment": {"sentiment": "neutral", "confidence": 0.7294672727584839}}, {"line_number": 3, "original_text": "polluting cannot be stopped by a few political decisions, hoping the problem will go away. We will all be affected for generations to\n", "sentiment": {"sentiment": "neutral", "confidence": 0.5027934908866882}}, {"line_number": 4, "original_text": "\n", "sentiment": {"sentiment": "neutral", "confidence": 0.9320765733718872}}, {"line_number": 5, "original_text": "come. The actions taken now can only mitigate these effects. However without serious action now, life on Earth will be far worse.\n", "sentiment": {"sentiment": "negative", "confidence": 0.655704140663147}}, {"line_number": 6, "original_text": "Show strength, vision and integrity in leading the way. Kia kaha.\n", "sentiment": {"sentiment": "positive", "confidence": 0.9533525109291077}}], "key_phrases": [{"Score": 0.9999997615814813, "Text": "The Bill"}, {"Score": 0.9999946952257818, "Text": "'s title"}, {"Score": 0.9999999701976798, "Text": "The Xero Emissions Bill"}, {"Score": 0.9999995231630692, "Text": "it"}, {"Score": 0.9999525179241481, "Text": "all greenhouse gases"}, {"Score": 0.57092419659957, "Text": "just"}, {"Score": 0.9196071827337445, "Text": "carbon"}, {"Score": 0.9999989271187127, "Text": "The utmost urgency"}, {"Score": 0.9999998807907282, "Text": "the Climate Change Commission"}, {"Score": 0.9999997019769058, "Text": "The changes"}, {"Score": 1.0, "Text": "motion"}, {"Score": 1.0, "Text": "decades"}, {"Score": 0.9999999403953606, "Text": "global\npolluting"}, {"Score": 0.9999980330542275, "Text": "a few political decisions"}, {"Score": 1.0, "Text": "the problem"}, {"Score": 0.9999998807907247, "Text": "We"}, {"Score": 0.9999994039539004, "Text": "generations"}, {"Score": 0.999997317801407, "Text": "The actions"}, {"Score": 1.0, "Text": "these effects"}, {"Score": 0.9999827149588363, "Text": "serious action"}, {"Score": 0.9999967813595916, "Text": "life"}, {"Score": 1.0, "Text": "Earth"}, {"Score": 0.999898811720838, "Text": "strength, vision and integrity"}, {"Score": 0.9999986886995273, "Text": "the way"}, {"Score": 0.9941249199601004, "Text": "Kia"}], "topics": [{"topic": "000", "confidence": "1.0"}]}