{"sentiment": [{"line_number": 0, "original_text": "See earlier comment about linking carbon emissions to the place of final consumption, especially with regard to our meat and dairy\n", "sentiment": {"sentiment": "neutral", "confidence": 0.990928590297699}}, {"line_number": 1, "original_text": "\n", "sentiment": {"sentiment": "neutral", "confidence": 0.9320765733718872}}, {"line_number": 2, "original_text": "exports. Food consumed overseas by 40 million people should not be on the heads of 5 million New Zealanders, any more than a\n", "sentiment": {"sentiment": "neutral", "confidence": 0.5220771431922913}}, {"line_number": 3, "original_text": "laptop I buy should count against China. See: Druckman, A., & Jackson, T. (2009). The carbon footprint of UK households 1990\u20132004:\n", "sentiment": {"sentiment": "neutral", "confidence": 0.7320553064346313}}, {"line_number": 4, "original_text": "A socio-economically disaggregated, quasi-multi-regional input\u2013output model. Ecological Economics, 68(7), 2066-2077.\n", "sentiment": {"sentiment": "neutral", "confidence": 0.9686397314071655}}, {"line_number": 5, "original_text": "\n", "sentiment": {"sentiment": "neutral", "confidence": 0.9320765733718872}}, {"line_number": 6, "original_text": "doi:http://dx.doi.org/10.1016/j.ecolecon.2009.01.013. In terms of transport, a lot of emphasis is given to cycling (rightly), but, based\n", "sentiment": {"sentiment": "neutral", "confidence": 0.9099891185760498}}, {"line_number": 7, "original_text": "on Household Travel Survey statistics for Christchurch that I have analysed, while around half of all trips are within cycling range (6\n", "sentiment": {"sentiment": "neutral", "confidence": 0.983641505241394}}, {"line_number": 8, "original_text": "\n", "sentiment": {"sentiment": "neutral", "confidence": 0.9320765733718872}}, {"line_number": 9, "original_text": "km), these only make up 15% of the total distance travelled and, therefore, the carbon emissions. Trips over 20 km are less than 10%\n", "sentiment": {"sentiment": "neutral", "confidence": 0.7701107263565063}}, {"line_number": 10, "original_text": "of trips but account for nearly half the distance travelled. Cycling is important for health and urban design reasons, but to reduce\n", "sentiment": {"sentiment": "neutral", "confidence": 0.5928259491920471}}, {"line_number": 11, "original_text": "carbon emissions, we need to reduce the carbon on *long* and medium length journeys. I can cycle everywhere in town, but one\n", "sentiment": {"sentiment": "neutral", "confidence": 0.7982604503631592}}, {"line_number": 12, "original_text": "\n", "sentiment": {"sentiment": "neutral", "confidence": 0.9320765733718872}}, {"line_number": 13, "original_text": "driving holiday can undo all of those savings. That basically means rail - commuter rail and inter-city passenger rail, as well as for\n", "sentiment": {"sentiment": "neutral", "confidence": 0.7748449444770813}}, {"line_number": 14, "original_text": "freight. These options need to be the fastest and cheapest option. If they don't compete on speed and cost, they won't be adopted.\n", "sentiment": {"sentiment": "negative", "confidence": 0.8686330914497375}}, {"line_number": 15, "original_text": "\n", "sentiment": {"sentiment": "neutral", "confidence": 0.9320765733718872}}, {"line_number": 16, "original_text": "The carbon is in the longer trips, not the easily substitutible short trips.\n", "sentiment": {"sentiment": "negative", "confidence": 0.43730196356773376}}, {"line_number": 17, "original_text": "\n", "sentiment": {"sentiment": "neutral", "confidence": 0.9320765733718872}}, {"line_number": 18, "original_text": "\n", "sentiment": {"sentiment": "neutral", "confidence": 0.9320765733718872}}, {"line_number": 19, "original_text": "\n", "sentiment": {"sentiment": "neutral", "confidence": 0.9320765733718872}}, {"line_number": 20, "original_text": " \n", "sentiment": {"sentiment": "neutral", "confidence": 0.9320765733718872}}], "key_phrases": [{"Score": 0.9988474274997418, "Text": "earlier comment"}, {"Score": 0.9989909894849461, "Text": "carbon emissions"}, {"Score": 0.9999990463269377, "Text": "the place"}, {"Score": 0.999998688699641, "Text": "final consumption"}, {"Score": 0.6389214503999633, "Text": "regard"}, {"Score": 0.9657244136272994, "Text": "our meat and dairy\n\nexports"}, {"Score": 0.9992798987900375, "Text": "Food"}, {"Score": 0.9999264565663681, "Text": "40 million people"}, {"Score": 0.9998759230631897, "Text": "the heads"}, {"Score": 0.9993462393961886, "Text": "5 million New Zealanders"}, {"Score": 0.7013321644162912, "Text": "any more than"}, {"Score": 0.8051867932783434, "Text": "a\nlaptop"}, {"Score": 0.9992643050824983, "Text": "I"}, {"Score": 0.9999973774024795, "Text": "China"}, {"Score": 0.861526347926456, "Text": "See"}, {"Score": 0.9993162062598446, "Text": "Druckman, A."}, {"Score": 0.9836750731487288, "Text": "Jackson, T."}, {"Score": 0.9998842611792573, "Text": "2009"}, {"Score": 0.9982683419546472, "Text": "The carbon footprint"}, {"Score": 0.9959155321263516, "Text": "UK households"}, {"Score": 0.9604970944705944, "Text": "1990\u20132004"}, {"Score": 0.9787493345374326, "Text": "A socio-economically disaggregated, quasi-multi-regional input\u2013output model"}, {"Score": 0.999464860371693, "Text": "Ecological Economics"}, {"Score": 0.9914911451657634, "Text": "68"}, {"Score": 0.9869412712202158, "Text": "7"}, {"Score": 0.8660157579985527, "Text": "2066-2077"}, {"Score": 0.9083996077450691, "Text": "doi"}, {"Score": 0.558757664548139, "Text": "http://dx.doi.org/10.1016/j.ecolecon.2009.01.013"}, {"Score": 0.9999865295319578, "Text": "terms"}, {"Score": 0.9999942779868433, "Text": "transport"}, {"Score": 0.9999906421682152, "Text": "a lot"}, {"Score": 0.9998216947063541, "Text": "emphasis"}, {"Score": 0.9955107907623751, "Text": "Household Travel Survey statistics"}, {"Score": 0.9996197477942644, "Text": "Christchurch"}, {"Score": 0.9999614968828868, "Text": "I"}, {"Score": 0.6521253654935225, "Text": "around"}, {"Score": 0.9962588211656561, "Text": "all trips"}, {"Score": 0.9781237388416057, "Text": "cycling range"}, {"Score": 0.967819595730893, "Text": "6\n\nkm"}, {"Score": 0.9999656689032875, "Text": "these"}, {"Score": 0.9998237909664718, "Text": "15%"}, {"Score": 0.9999885164103626, "Text": "the total distance"}, {"Score": 0.9977392646381607, "Text": "the carbon emissions"}, {"Score": 0.9999920130413283, "Text": "Trips"}, {"Score": 0.9991360047829464, "Text": "20 km"}, {"Score": 0.9996792807946088, "Text": "less than 10%"}, {"Score": 0.9999994039539004, "Text": "trips"}, {"Score": 0.9997239626393416, "Text": "nearly half the distance"}, {"Score": 0.999997854237364, "Text": "Cycling"}, {"Score": 0.9995289083851832, "Text": "health and urban design reasons"}, {"Score": 0.9999854567613763, "Text": "carbon emissions"}, {"Score": 0.9999952316511552, "Text": "we"}, {"Score": 0.9999946952192164, "Text": "the carbon"}, {"Score": 0.6612290865607836, "Text": "long"}, {"Score": 0.5051683527418002, "Text": "*"}, {"Score": 0.8081809778253647, "Text": "medium length journeys"}, {"Score": 0.9999979734461775, "Text": "I"}, {"Score": 0.9999972581939645, "Text": "town"}, {"Score": 0.9999764769473389, "Text": "one\n\ndriving holiday"}, {"Score": 0.9999992847447459, "Text": "all"}, {"Score": 0.9999999403953606, "Text": "those savings"}, {"Score": 0.999800840946219, "Text": "That"}, {"Score": 0.9749301465910316, "Text": "rail - commuter rail and inter-city passenger rail"}, {"Score": 0.9999047608461067, "Text": "freight"}, {"Score": 0.9999973774028206, "Text": "These options"}, {"Score": 0.9999959945868068, "Text": "the fastest and cheapest option"}, {"Score": 0.9999982118638471, "Text": "they"}, {"Score": 0.9999935230399808, "Text": "speed and cost"}, {"Score": 0.9999997615814777, "Text": "they"}, {"Score": 0.9998833739217965, "Text": "The carbon"}, {"Score": 0.9999966621530423, "Text": "the longer trips"}, {"Score": 0.945222212950121, "Text": ","}, {"Score": 0.7537143890419654, "Text": "not the easily substitutible short trips"}], "topics": [{"topic": "002", "confidence": "1.0"}]}